bython/__init__.py
bython/importing.py
bython/logger.py
bython/parser.py
bython-0.8.data/data/man/man1/by2py.1
bython-0.8.data/data/man/man1/bython.1
bython-0.8.data/data/man/man1/py2by.1
bython-0.8.data/scripts/by2py
bython-0.8.data/scripts/bython
bython-0.8.data/scripts/py2by
bython-0.8.dist-info/METADATA
bython-0.8.dist-info/RECORD
bython-0.8.dist-info/WHEEL
bython-0.8.dist-info/top_level.txt
