Metadata-Version: 2.1
Name: bython
Version: 0.8
Summary: Python with braces
Home-page: https://github.com/mathialo/bython
Author: Mathias Lohne
Author-email: mathialo@ifi.uio.no
License: MIT
Platform: UNKNOWN
